README.txt
setup.cfg
setup.py
repoze/__init__.py
repoze.bfg.traversaladapter.egg-info/PKG-INFO
repoze.bfg.traversaladapter.egg-info/SOURCES.txt
repoze.bfg.traversaladapter.egg-info/dependency_links.txt
repoze.bfg.traversaladapter.egg-info/entry_points.txt
repoze.bfg.traversaladapter.egg-info/namespace_packages.txt
repoze.bfg.traversaladapter.egg-info/not-zip-safe
repoze.bfg.traversaladapter.egg-info/requires.txt
repoze.bfg.traversaladapter.egg-info/top_level.txt
repoze/bfg/__init__.py
repoze/bfg/traversaladapter/__init__.py
repoze/bfg/traversaladapter/tests.py