Metadata-Version: 1.0
Name: repoze.bfg.traversaladapter
Version: 0.1
Summary: Alternative model graph traverser for the repoze.bfg web framework which allows registering arbitrary adapters for the type or interface of model objects encountered during traversal.
Home-page: http://packages.python.org/repoze.bfg.traversaladapter
Author: F. Oliver Gathmann
Author-email: gathmann@ocelerate.org
License: BSD-derived (http://www.repoze.org/LICENSE.txt)
Keywords: bfg repoze.bfg traverser traversal adapter
Platform: UNKNOWN
Classifier: Intended Audience :: Developers
Classifier: Programming Language :: Python
